animation/__init__.py
animation/animation.py
terminal_animation-0.5.dist-info/METADATA
terminal_animation-0.5.dist-info/WHEEL
terminal_animation-0.5.dist-info/top_level.txt
terminal_animation-0.5.dist-info/RECORD
