Metadata-Version: 2.1
Name: terminal-animation
Version: 0.5
Summary: Decorators for terminal-based wait animations.
Home-page: https://github.com/SilasNiewierra/terminal_animation
Author: Silas Niewierra
Author-email: niewierra.silas@gmail.com
License: MIT
Keywords: terminal,animation,wait,waiting,status
Platform: UNKNOWN
Classifier: Intended Audience :: Developers
Classifier: License :: OSI Approved :: Apple Public Source License
Classifier: Natural Language :: English
Classifier: Programming Language :: Python :: 3
Classifier: Programming Language :: Python :: 3.3
Classifier: Programming Language :: Python :: 3.4
Classifier: Programming Language :: Python :: 3.5
Classifier: Programming Language :: Python :: 3.6
Classifier: Programming Language :: Python :: 3.7
Requires-Dist: colorama (==0.4.4)
Requires-Dist: commonmark (==0.9.1)
Requires-Dist: cursor (==1.3.4)
Requires-Dist: pychalk (==2.0.1)
Requires-Dist: Pygments (==2.8.1)
Requires-Dist: six (==1.15.0)
Requires-Dist: typing-extensions (==3.7.4.3)
